pygeomag/__init__.py
pygeomag/format.py
pygeomag/geomag.py
pygeomag/time.py
pygeomag/util.py
pygeomag/wmm/WMM.COF
pygeomag/wmm/WMM_2010.COF
pygeomag/wmm/WMM_2015.COF
pygeomag/wmm/WMM_2015v2.COF
pygeomag/wmm/wmm_2010.py
pygeomag/wmm/wmm_2015.py
pygeomag/wmm/wmm_2015v2.py
pygeomag/wmm/wmm_2020.py
pygeomag-1.0.2.dist-info/LICENSE
pygeomag-1.0.2.dist-info/METADATA
pygeomag-1.0.2.dist-info/WHEEL
pygeomag-1.0.2.dist-info/top_level.txt
pygeomag-1.0.2.dist-info/RECORD
