Metadata-Version: 2.1
Name: pygeomag
Version: 1.0.2
Summary: A python port of the World Magnetic Model (WMM)
Author: Justin Myers
Project-URL: Homepage, https://github.com/boxpet/pygeomag
Project-URL: Bug Tracker, https://github.com/boxpet/pygeomag/issues
Classifier: Development Status :: 4 - Beta
Classifier: Programming Language :: Python :: 3
Classifier: License :: OSI Approved :: MIT License
Classifier: Operating System :: OS Independent
Requires-Python: >=3.7
License-File: LICENSE
